{
    "machine": "combiner",
    "registryName": "exanimisC",
    "recipeTime": 10,
    "requirements": [
        {
            "type": "aspect",
            "io-type": "input",
            "aspect": "motus",
            "amount": 1
        },
        {
            "type": "aspect",
            "io-type": "input",
            "aspect": "mortuus",
            "amount": 1
        },
        {
            "type": "aspect",
            "io-type": "output",
            "aspect": "exanimis",
            "amount": 2
        }
    ]
}